llm_price_scraper/__init__.py
llm_price_scraper/enums.py
llm_price_scraper/models.py
llm_price_scraper/utils.py
llm_price_scraper/scrapers/__init__.py
llm_price_scraper/scrapers/base.py
llm_price_scraper/scrapers/botgenuity.py
llm_price_scraper/scrapers/docsbot.py
llm_price_scraper/scrapers/huggingface.py
llm_price_scraper/scrapers/huhuhang.py
llm_price_scraper/scrapers/openai.py
tests/__init__.py
tests/test_llm_pricing.py
llm_price_scraper-1.0.3.dist-info/LICENSE
llm_price_scraper-1.0.3.dist-info/METADATA
llm_price_scraper-1.0.3.dist-info/WHEEL
llm_price_scraper-1.0.3.dist-info/top_level.txt
llm_price_scraper-1.0.3.dist-info/RECORD
