Metadata-Version: 2.1
Name: llm_price_scraper
Version: 1.0.3
Summary: A simple Python SDK to scrape and retrieve pricing information for Large Language Models (LLMs) from an external webpage, with structured models for easy integration and usage.
Home-page: https://github.com/WilliamJlvt/llm_price_scraper
Author: WilliamJlvt
Author-email: william.jolivet@epitech.eu
Requires-Python: >=3.6
License-File: LICENSE
Requires-Dist: requests>=2.32.3
Requires-Dist: beautifulsoup4>=4.12.3
